<?xml version="1.0" encoding="utf-8"?>
<Root>
  <Item>
    <Title>For Those About To Rock We Salute You</Title>
  </Item>
  <Item>
    <Title>Let There Be Rock</Title>
  </Item>
  <Item>
    <Title>Deep Purple In Rock</Title>
  </Item>
  <Item>
    <Title>Rock In Rio [CD1]</Title>
  </Item>
  <Item>
    <Title>Rock In Rio [CD2]</Title>
  </Item>
  <Item>
    <Title>Pure Cult: The Best Of The Cult (For Rockers, Ravers, Lovers &amp; Sinners) [UK]</Title>
  </Item>
  <Item>
    <Title>Hot Rocks, 1964-1971 (Disc 1)</Title>
  </Item>
</Root>